webdriver_pool/__init__.py
webdriver_pool/webdriver_item.py
webdriver_pool/webdriver_pool.py
webdriver_pool/webdriver_pool_config.py
webdriver_pool-1.0.1.dist-info/DESCRIPTION.rst
webdriver_pool-1.0.1.dist-info/METADATA
webdriver_pool-1.0.1.dist-info/RECORD
webdriver_pool-1.0.1.dist-info/WHEEL
webdriver_pool-1.0.1.dist-info/metadata.json
webdriver_pool-1.0.1.dist-info/top_level.txt
